colorize/__init__.py
colorize/__main__.py
colorize/colorize.py
tests/integration/__init__.py
tests/unit/__init__.py
tests/unit/color_test.py
tests/unit/printer_test.py
colorize-1.1.0.dist-info/METADATA
colorize-1.1.0.dist-info/WHEEL
colorize-1.1.0.dist-info/entry_points.txt
colorize-1.1.0.dist-info/top_level.txt
colorize-1.1.0.dist-info/RECORD
